LICENSE
README.rst
setup.py
test_zenlayercloud_sdk_python.egg-info/PKG-INFO
test_zenlayercloud_sdk_python.egg-info/SOURCES.txt
test_zenlayercloud_sdk_python.egg-info/dependency_links.txt
test_zenlayercloud_sdk_python.egg-info/requires.txt
test_zenlayercloud_sdk_python.egg-info/top_level.txt
zenlayercloud/__init__.py
zenlayercloud/test.py
zenlayercloud/bmc/__init__.py
zenlayercloud/bmc/v20221120/__init__.py
zenlayercloud/bmc/v20221120/bmc_client.py
zenlayercloud/bmc/v20221120/models.py
zenlayercloud/common/__init__.py
zenlayercloud/common/abstract_client.py
zenlayercloud/common/abstract_model.py
zenlayercloud/common/config.py
zenlayercloud/common/credential.py
zenlayercloud/common/request.py
zenlayercloud/common/response.py
zenlayercloud/common/utils.py
zenlayercloud/common/excpetion/__init__.py
zenlayercloud/common/excpetion/error_code.py
zenlayercloud/common/excpetion/zenlayer_cloud_sdk_exception.py