Metadata-Version: 2.1
Name: test-zenlayercloud-sdk-python
Version: 2.0.1
Summary: Test pZenlayer Cloud SDK for Python
Home-page: https://github.com/wolfgangzhu/zenlayercloud-sdk-python
Author: Zenlayer Cloud
Maintainer-email: zenlayercloudapi@zenlayer.com
License: Apache License 2.0
Platform: any
Classifier: Development Status :: 5 - Production/Stable
Classifier: Intended Audience :: Developers
Classifier: License :: OSI Approved :: Apache Software License
Classifier: Programming Language :: Python
Classifier: Programming Language :: Python :: 2.7
Classifier: Programming Language :: Python :: 3
Classifier: Programming Language :: Python :: 3.7
Classifier: Programming Language :: Python :: 3.8
Classifier: Programming Language :: Python :: 3.9
Classifier: Programming Language :: Python :: 3.10
License-File: LICENSE
